gadopenapi/__init__.py
gadopenapi/const/__init__.py
gadopenapi/const/fastapi.py
gadopenapi/const/pydantic.py
gadopenapi/const/specification.py
gadopenapi/const/symbols.py
gadopenapi/extensions/__init__.py
gadopenapi/extensions/affix/__init__.py
gadopenapi/extensions/affix/handlers.py
gadopenapi/extensions/errors/__init__.py
gadopenapi/extensions/errors/exceptions.py
gadopenapi/extensions/errors/utils.py
gadopenapi/extensions/operationid/__init__.py
gadopenapi/extensions/operationid/handlers.py
gadopenapi/utils/__init__.py
gadopenapi/utils/specification.py
tests/__init__.py
tests/test_init.py
gadopenapi-0.0.3.dist-info/LICENSE
gadopenapi-0.0.3.dist-info/METADATA
gadopenapi-0.0.3.dist-info/WHEEL
gadopenapi-0.0.3.dist-info/top_level.txt
gadopenapi-0.0.3.dist-info/RECORD
